rcsb/__init__.py
rcsb/utils/__init__.py
rcsb/utils/chemref/AtcProvider.py
rcsb/utils/chemref/BirdProvider.py
rcsb/utils/chemref/CARDProvider.py
rcsb/utils/chemref/CODProvider.py
rcsb/utils/chemref/ChEMBLProvider.py
rcsb/utils/chemref/ChemCompModelProvider.py
rcsb/utils/chemref/ChemCompProvider.py
rcsb/utils/chemref/DrugBankProvider.py
rcsb/utils/chemref/DrugBankReader.py
rcsb/utils/chemref/DrugCentralProvider.py
rcsb/utils/chemref/PharosProvider.py
rcsb/utils/chemref/PharosReadSqlDump.py
rcsb/utils/chemref/Pharos_dump_tables.sh
rcsb/utils/chemref/PsiModProvider.py
rcsb/utils/chemref/PubChemProvider.py
rcsb/utils/chemref/PubChemUtils.py
rcsb/utils/chemref/RcsbLigandScoreProvider.py
rcsb/utils/chemref/ResidProvider.py
rcsb/utils/chemref/ResidReader.py
rcsb/utils/chemref/__init__.py
rcsb_utils_chemref-0.96.dist-info/METADATA
rcsb_utils_chemref-0.96.dist-info/WHEEL
rcsb_utils_chemref-0.96.dist-info/licenses/LICENSE
rcsb_utils_chemref-0.96.dist-info/RECORD
