Metadata-Version: 2.4
Name: rcsb.utils.chemref
Version: 0.96
Summary: RCSB Python Chemical Reference Data Utility Classes
Project-URL: Homepage, https://github.com/rcsb/py-rcsb_utils_chemref
Author-email: John Westbrook <john.westbrook@rcsb.org>
Maintainer-email: Dennis Piehl <dennis.piehl@rcsb.org>
License-Expression: Apache-2.0
License-File: LICENSE
Classifier: Development Status :: 5 - Production/Stable
Classifier: Intended Audience :: Developers
Classifier: Natural Language :: English
Classifier: Programming Language :: Python
Classifier: Programming Language :: Python :: 3
Classifier: Programming Language :: Python :: 3.13
Requires-Python: >=3.9
Requires-Dist: chembl-webresource-client>=0.10.2
Requires-Dist: mmcif>=1.0.0
Requires-Dist: networkx>=2.4
Requires-Dist: obonet>=0.2.5
Requires-Dist: rcsb-utils-config>=0.40
Requires-Dist: rcsb-utils-io>=1.50
Provides-Extra: tests
Requires-Dist: black>=21.5b1; extra == 'tests'
Requires-Dist: check-manifest; extra == 'tests'
Requires-Dist: coverage; extra == 'tests'
Requires-Dist: flake8; extra == 'tests'
Requires-Dist: pylint; extra == 'tests'
Requires-Dist: tox; extra == 'tests'
